cdktf_cdktf_provider_databricks/__init__.py
cdktf_cdktf_provider_databricks/py.typed
cdktf_cdktf_provider_databricks/_jsii/__init__.py
cdktf_cdktf_provider_databricks/_jsii/provider-databricks@15.14.0.jsii.tgz
cdktf_cdktf_provider_databricks/access_control_rule_set/__init__.py
cdktf_cdktf_provider_databricks/account_federation_policy/__init__.py
cdktf_cdktf_provider_databricks/account_network_policy/__init__.py
cdktf_cdktf_provider_databricks/account_setting_v2/__init__.py
cdktf_cdktf_provider_databricks/aibi_dashboard_embedding_access_policy_setting/__init__.py
cdktf_cdktf_provider_databricks/aibi_dashboard_embedding_approved_domains_setting/__init__.py
cdktf_cdktf_provider_databricks/alert/__init__.py
cdktf_cdktf_provider_databricks/alert_v2/__init__.py
cdktf_cdktf_provider_databricks/app/__init__.py
cdktf_cdktf_provider_databricks/apps_settings_custom_template/__init__.py
cdktf_cdktf_provider_databricks/artifact_allowlist/__init__.py
cdktf_cdktf_provider_databricks/automatic_cluster_update_workspace_setting/__init__.py
cdktf_cdktf_provider_databricks/aws_s3_mount/__init__.py
cdktf_cdktf_provider_databricks/azure_adls_gen1_mount/__init__.py
cdktf_cdktf_provider_databricks/azure_adls_gen2_mount/__init__.py
cdktf_cdktf_provider_databricks/azure_blob_mount/__init__.py
cdktf_cdktf_provider_databricks/budget/__init__.py
cdktf_cdktf_provider_databricks/budget_policy/__init__.py
cdktf_cdktf_provider_databricks/catalog/__init__.py
cdktf_cdktf_provider_databricks/catalog_workspace_binding/__init__.py
cdktf_cdktf_provider_databricks/cluster/__init__.py
cdktf_cdktf_provider_databricks/cluster_policy/__init__.py
cdktf_cdktf_provider_databricks/compliance_security_profile_workspace_setting/__init__.py
cdktf_cdktf_provider_databricks/connection/__init__.py
cdktf_cdktf_provider_databricks/credential/__init__.py
cdktf_cdktf_provider_databricks/custom_app_integration/__init__.py
cdktf_cdktf_provider_databricks/dashboard/__init__.py
cdktf_cdktf_provider_databricks-15.14.0.dist-info/LICENSE
cdktf_cdktf_provider_databricks-15.14.0.dist-info/METADATA
cdktf_cdktf_provider_databricks-15.14.0.dist-info/WHEEL
cdktf_cdktf_provider_databricks-15.14.0.dist-info/top_level.txt
cdktf_cdktf_provider_databricks-15.14.0.dist-info/RECORD
